README.md
setup.cfg
setup.py
incremental_counter/__init__.py
incremental_counter.egg-info/PKG-INFO
incremental_counter.egg-info/SOURCES.txt
incremental_counter.egg-info/dependency_links.txt
incremental_counter.egg-info/top_level.txt