Metadata-Version: 2.1
Name: incremental-counter
Version: 0.1.3
Summary: Incremental Counter
Home-page: https://github.com/UedaTakeyuki/incremental_counter
Author: Takeyuki UEDA
Author-email: gde00107@nifty.com
License: MIT
Keywords: sensor,IoT
Platform: UNKNOWN
Classifier: Development Status :: 4 - Beta
Classifier: Programming Language :: Python
Classifier: Topic :: Terminals
